orca_parser/G16_parse.py
orca_parser/HessianTools.py
orca_parser/ORCAParse.py
orca_parser/__init__.py
orca_parser/ams_parse.py
orca_parser/parse_engrad.py
orca_parser/parse_scan.py
orca_parser/version.py
orca_parser-0.2.8.dist-info/LICENSE
orca_parser-0.2.8.dist-info/METADATA
orca_parser-0.2.8.dist-info/WHEEL
orca_parser-0.2.8.dist-info/top_level.txt
orca_parser-0.2.8.dist-info/RECORD
