Metadata-Version: 2.1
Name: orca-parser
Version: 0.2.8
Summary: A module for parse ORCA output files including hessians (.hess) files
Home-page: https://github.com/avanteijlingen/ORCA-Parser
Author: Alexander van Teijlingen
Author-email: a.vant@linuxmail.org
License: BSD 2-clause
Classifier: Intended Audience :: Science/Research
Classifier: Programming Language :: Python :: 3.10
License-File: LICENSE
Requires-Dist: ase
Requires-Dist: pandas
Requires-Dist: numpy
